chromax/__init__.py
chromax/functional.py
chromax/index_functions.py
chromax/simulator.py
chromax/trait_model.py
chromax/typing.py
chromax/sample_data/__init__.py
chromax/sample_data/genetic_map.csv
chromax/sample_data/genome.npy
chromax-0.0.2a0.dist-info/LICENSE
chromax-0.0.2a0.dist-info/METADATA
chromax-0.0.2a0.dist-info/WHEEL
chromax-0.0.2a0.dist-info/top_level.txt
chromax-0.0.2a0.dist-info/RECORD
