Metadata-Version: 2.1
Name: chromax
Version: 0.0.2a0
Summary: Breeding simulator based on JAX
Home-page: https://github.com/younik/chromax
Author: Omar Younis
Author-email: omar.younis98@gmail.com
License: bsd-3-clause
Project-URL: Code, https://github.com/kora-labs/chromax
Project-URL: Documentation, https://chromax.readthedocs.io/
Keywords: Breeding,simulator,JAX,chromosome,genetics,bioinformatics
Classifier: Programming Language :: Python :: 3
Classifier: Programming Language :: Python :: 3.8
Classifier: Programming Language :: Python :: 3.9
Classifier: Programming Language :: Python :: 3.10
Classifier: Programming Language :: Python :: 3.11
Requires-Python: >=3.8
License-File: LICENSE
Requires-Dist: numpy
Requires-Dist: pandas
Requires-Dist: jax
Requires-Dist: jaxlib
Requires-Dist: jaxtyping
